kswutils_signal/__init__.py
kswutils_signal/calculator.py
kswutils_signal/frequency_analysis.py
kswutils_signal-0.0.4.dist-info/METADATA
kswutils_signal-0.0.4.dist-info/WHEEL
kswutils_signal-0.0.4.dist-info/licenses/LICENSE
kswutils_signal-0.0.4.dist-info/RECORD
